{"tmpl_params":{"comments_indent":"100"},"tmpl_core":{"comments_sort":"ctime ASC","comments_author_avatar":"0","comments_author_avatar_width":"100","comments_author_avatar_height":"100","comments_editor":"none","comments_time_format":"l, d F Y","comments_nested":"10","comments_subscribe":"0","comments_title":"1","comments_username":"1","comments_date":"1","comments_rss_button":"1","comemnts_fold":"1","comemnts_limit_box":"1","comments_pagination":"20","comments_title_lbl":"Comments","comments_add_title_lbl":"Add New Comment","comments_button_title_lbl":"Post Comment"}}